sversion/__init__.py
sversion/CHANGELOG.md
sversion/contracts.py
sversion/error_handling.py
sversion/pyproject_toml_based.py
sversion/version_file_based.py
sversion-2.2.0.dist-info/LICENSE
sversion-2.2.0.dist-info/METADATA
sversion-2.2.0.dist-info/WHEEL
sversion-2.2.0.dist-info/RECORD
