Metadata-Version: 2.3
Name: sversion
Version: 2.2.0
Summary: Simple version management in Python
License: MIT
Author: Kostiantyn Chomakov
Author-email: kostiantyn.chomakov@gmail.com
Requires-Python: >=3.13,<4.0
Classifier: License :: OSI Approved :: MIT License
Classifier: Operating System :: OS Independent
Classifier: Programming Language :: Python :: 3
Classifier: Programming Language :: Python :: 3.13
Project-URL: Homepage, https://github.com/takinosaji/partial-injector
Project-URL: Repository, https://github.com/takinosaji/partial-injector
